{"CollectionItemName":"Item","Config":{"JsonNumericMaxPrecision":false,"XEv3Compatibility":false},"ExposedName":"Item","ExposedNamespace":"IS2","HasJsonName":false,"Index":0,"IsCollection":true,"IsWrappedSerialized":true,"JsonInclude":"idJsonNoProperty","JsonName":"DVelop_Menu","KBLocation":"C:\\KB\\IS2","Name":"DVelop_Menu","XmlCollectionItemName":"Item","XmlCollectionItemNamespace":null,"XmlInclude":"idXmlIncludeAlways","XmlName":"DVelop_Menu","XmlNamespace":null,"CSCompilationIncludes":[],"FullItemName":"DVelop_Menu.Item","FullName":"DVelop_Menu","Items":[{"CollectionItemName":null,"Config":{"JsonNumericMaxPrecision":false,"XEv3Compatibility":false},"ExposedName":null,"ExposedNamespace":null,"HasJsonName":false,"Index":0,"IsCollection":false,"IsWrappedSerialized":false,"JsonInclude":"idJsonEmpty","JsonName":"id","KBLocation":"C:\\KB\\IS2","Name":"id","XmlCollectionItemName":null,"XmlCollectionItemNamespace":null,"XmlInclude":"idXmlIncludeAlways","XmlName":"id","XmlNamespace":null,"CSharpRef":null,"CustomType":null,"Decimals":0,"InitialValue":null,"InitialValueSpec":null,"InternalType":13,"JavaRef":null,"Length":40,"SoapType":"","XmlDateSerialization":"idXmlDateDefaultFormat","XmlType":"Element"},{"CollectionItemName":null,"Config":{"JsonNumericMaxPrecision":false,"XEv3Compatibility":false},"ExposedName":null,"ExposedNamespace":null,"HasJsonName":false,"Index":1,"IsCollection":false,"IsWrappedSerialized":false,"JsonInclude":"idJsonEmpty","JsonName":"tooltip","KBLocation":"C:\\KB\\IS2","Name":"tooltip","XmlCollectionItemName":null,"XmlCollectionItemNamespace":null,"XmlInclude":"idXmlIncludeAlways","XmlName":"tooltip","XmlNamespace":null,"CSharpRef":null,"CustomType":null,"Decimals":0,"InitialValue":null,"InitialValueSpec":null,"InternalType":13,"JavaRef":null,"Length":40,"SoapType":"","XmlDateSerialization":"idXmlDateDefaultFormat","XmlType":"Element"},{"CollectionItemName":null,"Config":{"JsonNumericMaxPrecision":false,"XEv3Compatibility":false},"ExposedName":null,"ExposedNamespace":null,"HasJsonName":false,"Index":2,"IsCollection":false,"IsWrappedSerialized":false,"JsonInclude":"idJsonEmpty","JsonName":"link","KBLocation":"C:\\KB\\IS2","Name":"link","XmlCollectionItemName":null,"XmlCollectionItemNamespace":null,"XmlInclude":"idXmlIncludeAlways","XmlName":"link","XmlNamespace":null,"CSharpRef":null,"CustomType":null,"Decimals":0,"InitialValue":null,"InitialValueSpec":null,"InternalType":13,"JavaRef":null,"Length":40,"SoapType":"","XmlDateSerialization":"idXmlDateDefaultFormat","XmlType":"Element"},{"CollectionItemName":null,"Config":{"JsonNumericMaxPrecision":false,"XEv3Compatibility":false},"ExposedName":null,"ExposedNamespace":null,"HasJsonName":false,"Index":3,"IsCollection":false,"IsWrappedSerialized":false,"JsonInclude":"idJsonEmpty","JsonName":"linkTarget","KBLocation":"C:\\KB\\IS2","Name":"linkTarget","XmlCollectionItemName":null,"XmlCollectionItemNamespace":null,"XmlInclude":"idXmlIncludeAlways","XmlName":"linkTarget","XmlNamespace":null,"CSharpRef":null,"CustomType":null,"Decimals":0,"InitialValue":null,"InitialValueSpec":null,"InternalType":13,"JavaRef":null,"Length":40,"SoapType":"","XmlDateSerialization":"idXmlDateDefaultFormat","XmlType":"Element"},{"CollectionItemName":null,"Config":{"JsonNumericMaxPrecision":false,"XEv3Compatibility":false},"ExposedName":null,"ExposedNamespace":null,"HasJsonName":false,"Index":4,"IsCollection":false,"IsWrappedSerialized":false,"JsonInclude":"idJsonEmpty","JsonName":"iconClass","KBLocation":"C:\\KB\\IS2","Name":"iconClass","XmlCollectionItemName":null,"XmlCollectionItemNamespace":null,"XmlInclude":"idXmlIncludeAlways","XmlName":"iconClass","XmlNamespace":null,"CSharpRef":null,"CustomType":null,"Decimals":0,"InitialValue":null,"InitialValueSpec":null,"InternalType":13,"JavaRef":null,"Length":40,"SoapType":"","XmlDateSerialization":"idXmlDateDefaultFormat","XmlType":"Element"},{"CollectionItemName":null,"Config":{"JsonNumericMaxPrecision":false,"XEv3Compatibility":false},"ExposedName":null,"ExposedNamespace":null,"HasJsonName":false,"Index":5,"IsCollection":false,"IsWrappedSerialized":false,"JsonInclude":"idJsonEmpty","JsonName":"caption","KBLocation":"C:\\KB\\IS2","Name":"caption","XmlCollectionItemName":null,"XmlCollectionItemNamespace":null,"XmlInclude":"idXmlIncludeAlways","XmlName":"caption","XmlNamespace":null,"CSharpRef":null,"CustomType":null,"Decimals":0,"InitialValue":null,"InitialValueSpec":null,"InternalType":13,"JavaRef":null,"Length":40,"SoapType":"","XmlDateSerialization":"idXmlDateDefaultFormat","XmlType":"Element"},{"CollectionItemName":null,"Config":{"JsonNumericMaxPrecision":false,"XEv3Compatibility":false},"ExposedName":null,"ExposedNamespace":null,"HasJsonName":false,"Index":6,"IsCollection":false,"IsWrappedSerialized":false,"JsonInclude":"idJsonEmpty","JsonName":"authorizationKey","KBLocation":"C:\\KB\\IS2","Name":"authorizationKey","XmlCollectionItemName":null,"XmlCollectionItemNamespace":null,"XmlInclude":"idXmlIncludeAlways","XmlName":"authorizationKey","XmlNamespace":null,"CSharpRef":null,"CustomType":null,"Decimals":0,"InitialValue":null,"InitialValueSpec":null,"InternalType":13,"JavaRef":null,"Length":40,"SoapType":"","XmlDateSerialization":"idXmlDateDefaultFormat","XmlType":"Element"},{"CollectionItemName":null,"Config":{"JsonNumericMaxPrecision":false,"XEv3Compatibility":false},"ExposedName":null,"ExposedNamespace":null,"HasJsonName":false,"Index":7,"IsCollection":false,"IsWrappedSerialized":false,"JsonInclude":"idJsonEmpty","JsonName":"additionalData","KBLocation":"C:\\KB\\IS2","Name":"additionalData","XmlCollectionItemName":null,"XmlCollectionItemNamespace":null,"XmlInclude":"idXmlIncludeAlways","XmlName":"additionalData","XmlNamespace":null,"CSharpRef":null,"CustomType":null,"Decimals":0,"InitialValue":null,"InitialValueSpec":null,"InternalType":13,"JavaRef":null,"Length":40,"SoapType":"","XmlDateSerialization":"idXmlDateDefaultFormat","XmlType":"Element"},{"CollectionItemName":null,"Config":{"JsonNumericMaxPrecision":false,"XEv3Compatibility":false},"ExposedName":null,"ExposedNamespace":null,"HasJsonName":false,"Index":8,"IsCollection":false,"IsWrappedSerialized":false,"JsonInclude":"idJsonEmpty","JsonName":"submenuImage","KBLocation":"C:\\KB\\IS2","Name":"submenuImage","XmlCollectionItemName":null,"XmlCollectionItemNamespace":null,"XmlInclude":"idXmlIncludeAlways","XmlName":"submenuImage","XmlNamespace":null,"CSharpRef":null,"CustomType":null,"Decimals":0,"InitialValue":null,"InitialValueSpec":null,"InternalType":7,"JavaRef":null,"Length":4,"SoapType":"","XmlDateSerialization":"idXmlDateDefaultFormat","XmlType":"Element"},{"CollectionItemName":"Item","Config":{"JsonNumericMaxPrecision":false,"XEv3Compatibility":false},"ExposedName":"DVelop_Menu","ExposedNamespace":null,"HasJsonName":false,"Index":9,"IsCollection":true,"IsWrappedSerialized":true,"JsonInclude":"idJsonNoProperty","JsonName":"subItems","KBLocation":"C:\\KB\\IS2","Name":"subItems","XmlCollectionItemName":"Item","XmlCollectionItemNamespace":null,"XmlInclude":"idXmlIncludeAlways","XmlName":"subItems","XmlNamespace":null,"CSharpRef":null,"CustomType":"GeneXus.Programs.wwpbaseobjects.SdtDVelop_Menu_Item","Decimals":0,"InitialValue":null,"InitialValueSpec":null,"InternalType":254,"JavaRef":null,"Length":4,"SoapType":"","XmlDateSerialization":"idXmlDateDefaultFormat","XmlType":"Element"}],"Levels":[],"RestContract":"WWPBaseObjects\\DVelop_Menu.Item"}