{"CollectionItemName":"TabOptionsItem","Config":{"JsonNumericMaxPrecision":false,"XEv3Compatibility":false},"ExposedName":"TabOptionsItem","ExposedNamespace":"IS2","HasJsonName":false,"Index":0,"IsCollection":true,"IsWrappedSerialized":true,"JsonInclude":"idJsonNoProperty","JsonName":"WWPTabOptions","KBLocation":"C:\\KB\\IS2","Name":"WWPTabOptions","XmlCollectionItemName":"TabOptionsItem","XmlCollectionItemNamespace":null,"XmlInclude":"idXmlIncludeAlways","XmlName":"WWPTabOptions","XmlNamespace":null,"CSCompilationIncludes":[],"FullItemName":"WWPTabOptions.TabOptionsItem","FullName":"WWPTabOptions","Items":[{"CollectionItemName":null,"Config":{"JsonNumericMaxPrecision":false,"XEv3Compatibility":false},"ExposedName":null,"ExposedNamespace":null,"HasJsonName":false,"Index":0,"IsCollection":false,"IsWrappedSerialized":false,"JsonInclude":"idJsonEmpty","JsonName":"Code","KBLocation":"C:\\KB\\IS2","Name":"Code","XmlCollectionItemName":null,"XmlCollectionItemNamespace":null,"XmlInclude":"idXmlIncludeAlways","XmlName":"Code","XmlNamespace":null,"CSharpRef":null,"CustomType":null,"Decimals":0,"InitialValue":null,"InitialValueSpec":null,"InternalType":5,"JavaRef":null,"Length":50,"SoapType":"","XmlDateSerialization":"idXmlDateDefaultFormat","XmlType":"Element"},{"CollectionItemName":null,"Config":{"JsonNumericMaxPrecision":false,"XEv3Compatibility":false},"ExposedName":null,"ExposedNamespace":null,"HasJsonName":false,"Index":1,"IsCollection":false,"IsWrappedSerialized":false,"JsonInclude":"idJsonEmpty","JsonName":"Description","KBLocation":"C:\\KB\\IS2","Name":"Description","XmlCollectionItemName":null,"XmlCollectionItemNamespace":null,"XmlInclude":"idXmlIncludeAlways","XmlName":"Description","XmlNamespace":null,"CSharpRef":null,"CustomType":null,"Decimals":0,"InitialValue":null,"InitialValueSpec":null,"InternalType":13,"JavaRef":null,"Length":255,"SoapType":"","XmlDateSerialization":"idXmlDateDefaultFormat","XmlType":"Element"},{"CollectionItemName":null,"Config":{"JsonNumericMaxPrecision":false,"XEv3Compatibility":false},"ExposedName":null,"ExposedNamespace":null,"HasJsonName":false,"Index":2,"IsCollection":false,"IsWrappedSerialized":false,"JsonInclude":"idJsonEmpty","JsonName":"Link","KBLocation":"C:\\KB\\IS2","Name":"Link","XmlCollectionItemName":null,"XmlCollectionItemNamespace":null,"XmlInclude":"idXmlIncludeAlways","XmlName":"Link","XmlNamespace":null,"CSharpRef":null,"CustomType":null,"Decimals":0,"InitialValue":null,"InitialValueSpec":null,"InternalType":13,"JavaRef":null,"Length":1000,"SoapType":"","XmlDateSerialization":"idXmlDateDefaultFormat","XmlType":"Element"},{"CollectionItemName":null,"Config":{"JsonNumericMaxPrecision":false,"XEv3Compatibility":false},"ExposedName":null,"ExposedNamespace":null,"HasJsonName":false,"Index":3,"IsCollection":false,"IsWrappedSerialized":false,"JsonInclude":"idJsonEmpty","JsonName":"WebComponent","KBLocation":"C:\\KB\\IS2","Name":"WebComponent","XmlCollectionItemName":null,"XmlCollectionItemNamespace":null,"XmlInclude":"idXmlIncludeAlways","XmlName":"WebComponent","XmlNamespace":null,"CSharpRef":null,"CustomType":null,"Decimals":0,"InitialValue":null,"InitialValueSpec":null,"InternalType":13,"JavaRef":null,"Length":1000,"SoapType":"","XmlDateSerialization":"idXmlDateDefaultFormat","XmlType":"Element"},{"CollectionItemName":null,"Config":{"JsonNumericMaxPrecision":false,"XEv3Compatibility":false},"ExposedName":null,"ExposedNamespace":null,"HasJsonName":false,"Index":4,"IsCollection":false,"IsWrappedSerialized":false,"JsonInclude":"idJsonEmpty","JsonName":"IncludeInPanel","KBLocation":"C:\\KB\\IS2","Name":"IncludeInPanel","XmlCollectionItemName":null,"XmlCollectionItemNamespace":null,"XmlInclude":"idXmlIncludeAlways","XmlName":"IncludeInPanel","XmlNamespace":null,"CSharpRef":null,"CustomType":null,"Decimals":0,"InitialValue":null,"InitialValueSpec":null,"InternalType":4,"JavaRef":null,"Length":1,"SoapType":"","XmlDateSerialization":"idXmlDateDefaultFormat","XmlType":"Element"},{"CollectionItemName":null,"Config":{"JsonNumericMaxPrecision":false,"XEv3Compatibility":false},"ExposedName":null,"ExposedNamespace":null,"HasJsonName":false,"Index":5,"IsCollection":false,"IsWrappedSerialized":false,"JsonInclude":"idJsonEmpty","JsonName":"CollapsedByDefault","KBLocation":"C:\\KB\\IS2","Name":"CollapsedByDefault","XmlCollectionItemName":null,"XmlCollectionItemNamespace":null,"XmlInclude":"idXmlIncludeAlways","XmlName":"CollapsedByDefault","XmlNamespace":null,"CSharpRef":null,"CustomType":null,"Decimals":0,"InitialValue":null,"InitialValueSpec":null,"InternalType":15,"JavaRef":null,"Length":10,"SoapType":"","XmlDateSerialization":"idXmlDateDefaultFormat","XmlType":"Element"},{"CollectionItemName":null,"Config":{"JsonNumericMaxPrecision":false,"XEv3Compatibility":false},"ExposedName":null,"ExposedNamespace":null,"HasJsonName":false,"Index":6,"IsCollection":false,"IsWrappedSerialized":false,"JsonInclude":"idJsonEmpty","JsonName":"Collapsable","KBLocation":"C:\\KB\\IS2","Name":"Collapsable","XmlCollectionItemName":null,"XmlCollectionItemNamespace":null,"XmlInclude":"idXmlIncludeAlways","XmlName":"Collapsable","XmlNamespace":null,"CSharpRef":null,"CustomType":null,"Decimals":0,"InitialValue":null,"InitialValueSpec":null,"InternalType":15,"JavaRef":null,"Length":10,"SoapType":"","XmlDateSerialization":"idXmlDateDefaultFormat","XmlType":"Element"}],"Levels":[],"RestContract":"WWPBaseObjects\\WWPTabOptions.TabOptionsItem"}